<?xml version="1.0" standalone="no"?>

<graph>

	<description>
	The llvm Roll - http://llvm.org
	</description>

	<copyright>
	Copyright (c) 2000 - 2014 The Regents of the University of California.
	All rights reserved. Rocks(r) v6.1.1 www.rocksclusters.org
	</copyright>

	<!-- add edges here -->
	<edge from="base">
		<to>llvm-base</to>
	</edge>

	<!-- enforce post section ordering -->
	<!-- llvm-base post sections execute after base post sections -->
	<order head="base">
		<tail>llvm-base</tail>
	</order>

</graph>
